qt_dev
