Metadata-Version: 2.4
Name: amulet-qt-dev
Version: 6.9.1.0a1
Summary: Qt6 compiled with dev files for linking.
Author: James Clare
Project-URL: Homepage, https://www.amuletmc.com
Project-URL: Repository, https://github.com/Amulet-Team/Amulet-qt-dev
Project-URL: Issues, https://github.com/Amulet-Team/Amulet-qt-dev/issues
Classifier: Programming Language :: Python :: 3
Classifier: Operating System :: OS Independent
Requires-Python: >=3.9
License-File: LICENSE
Dynamic: license-file
